{"_type":"export","__export_format":4,"__export_date":"2024-12-19T12:20:45.456Z","__export_source":"insomnia.desktop.app:v10.2.0","resources":[{"_id":"req_d4bb780c5d0a47e597d7d90702cf977e","parentId":"fld_5c12ab985797429e92d8106612215e81","modified":1734610750247,"created":1734610286443,"url":"http://127.0.0.1:8000/api/users/authenticated/","name":"Autenticação Usuario","description":"","method":"GET","body":{"mimeType":"application/json","text":""},"parameters":[],"headers":[{"name":"Content-Type","value":"application/json","id":"pair_311f50fc1c7e401b880ecb5b7557b219"},{"name":"User-Agent","value":"insomnia/10.2.0","id":"pair_80cbcd0a84484868931acc95708f9f09"}],"authentication":{"type":"bearer","token":"fd1e29d8c8732a895e58fb955073fc10e91b176f","prefix":"Token"},"metaSortKey":-1734610187083,"isPrivate":false,"pathParameters":[],"settingStoreCookies":true,"settingSendCookies":true,"settingDisableRenderRequestBody":false,"settingEncodeUrl":true,"settingRebuildPath":true,"settingFollowRedirects":"global","_type":"request"},{"_id":"fld_5c12ab985797429e92d8106612215e81","parentId":"wrk_991f9da46bd14e3da11302c4cc68657f","modified":1734610119188,"created":1734610119188,"name":"Usuario","description":"","environment":{},"environmentPropertyOrder":null,"metaSortKey":-1734610119188,"environmentType":"kv","_type":"request_group"},{"_id":"wrk_991f9da46bd14e3da11302c4cc68657f","parentId":null,"modified":1734546930846,"created":1734546930846,"name":"TCC","description":"","scope":"collection","_type":"workspace"},{"_id":"req_92aa904f30554c8998582772fe0da9c3","parentId":"fld_5c12ab985797429e92d8106612215e81","modified":1734610234061,"created":1734610123864,"url":"http://127.0.0.1:8000/api/users/register/","name":"Registra Usuario","description":"","method":"POST","body":{"mimeType":"application/json","text":"{\n    \"username\": \"leticia\",\n    \"password\": \"senha123\"\n}\n"},"parameters":[],"headers":[{"name":"Content-Type","value":"application/json"},{"name":"User-Agent","value":"insomnia/10.2.0"}],"authentication":{},"metaSortKey":-1734610186983,"isPrivate":false,"pathParameters":[],"settingStoreCookies":true,"settingSendCookies":true,"settingDisableRenderRequestBody":false,"settingEncodeUrl":true,"settingRebuildPath":true,"settingFollowRedirects":"global","_type":"request"},{"_id":"req_4506ad50cb64473abe0c060af1363bcb","parentId":"fld_5c12ab985797429e92d8106612215e81","modified":1734610266444,"created":1734610190074,"url":"http://127.0.0.1:8000/api/users/login/","name":"Login Usuario","description":"","method":"POST","body":{"mimeType":"application/json","text":"{\n    \"username\": \"leticia\",\n    \"password\": \"senha123\"\n}\n"},"parameters":[],"headers":[{"name":"Content-Type","value":"application/json"},{"name":"User-Agent","value":"insomnia/10.2.0"}],"authentication":{},"metaSortKey":-1734610186883,"isPrivate":false,"pathParameters":[],"settingStoreCookies":true,"settingSendCookies":true,"settingDisableRenderRequestBody":false,"settingEncodeUrl":true,"settingRebuildPath":true,"settingFollowRedirects":"global","_type":"request"},{"_id":"req_ad24a8d064994050b25a498e754efab2","parentId":"fld_b4347c58d5254f9aba43b9df126c8cf0","modified":1734549120991,"created":1734549104333,"url":"http://127.0.0.1:8000/api/presencas/","name":"Presenca","description":"","method":"GET","body":{},"parameters":[],"headers":[{"name":"User-Agent","value":"insomnia/10.2.0"}],"authentication":{},"metaSortKey":-1734549120883,"isPrivate":false,"pathParameters":[],"settingStoreCookies":true,"settingSendCookies":true,"settingDisableRenderRequestBody":false,"settingEncodeUrl":true,"settingRebuildPath":true,"settingFollowRedirects":"global","_type":"request"},{"_id":"fld_b4347c58d5254f9aba43b9df126c8cf0","parentId":"wrk_991f9da46bd14e3da11302c4cc68657f","modified":1734549098257,"created":1734549098257,"name":"Presenca","description":"","environment":{},"environmentPropertyOrder":null,"metaSortKey":-1734549098257,"environmentType":"kv","_type":"request_group"},{"_id":"req_8d463fdf62d14809a35c733b2b9a5460","parentId":"fld_b4347c58d5254f9aba43b9df126c8cf0","modified":1734549217441,"created":1734549123587,"url":"http://127.0.0.1:8000/api/presencas/","name":"Presenca","description":"","method":"POST","body":{"mimeType":"application/json","text":"{\n    \"data\": \"2024-12-18\",\n    \"aluno\": 2,         \n    \"materia\": 3,        \n    \"presente\": true     \n}\n"},"parameters":[],"headers":[{"name":"Content-Type","value":"application/json"},{"name":"User-Agent","value":"insomnia/10.2.0"}],"authentication":{},"metaSortKey":-1734549120783,"isPrivate":false,"pathParameters":[],"settingStoreCookies":true,"settingSendCookies":true,"settingDisableRenderRequestBody":false,"settingEncodeUrl":true,"settingRebuildPath":true,"settingFollowRedirects":"global","_type":"request"},{"_id":"req_5e771429bed44026b2db8ff0409502d8","parentId":"fld_b4347c58d5254f9aba43b9df126c8cf0","modified":1734549262544,"created":1734549220399,"url":"http://127.0.0.1:8000/api/presencas/1/","name":"Presenca","description":"","method":"PUT","body":{"mimeType":"application/json","text":"{\n    \"data\": \"2024-12-18\",\n    \"aluno\": 2,\n    \"materia\": 3,\n    \"presente\": false\n}\n"},"parameters":[],"headers":[{"name":"Content-Type","value":"application/json"},{"name":"User-Agent","value":"insomnia/10.2.0"}],"authentication":{},"metaSortKey":-1734549120683,"isPrivate":false,"pathParameters":[],"settingStoreCookies":true,"settingSendCookies":true,"settingDisableRenderRequestBody":false,"settingEncodeUrl":true,"settingRebuildPath":true,"settingFollowRedirects":"global","_type":"request"},{"_id":"req_36a61502ae024a509f902fa9b3900e18","parentId":"fld_b4347c58d5254f9aba43b9df126c8cf0","modified":1734549287883,"created":1734549264352,"url":"http://127.0.0.1:8000/api/presencas/1/","name":"Presenca","description":"","method":"DELETE","body":{},"parameters":[],"headers":[{"name":"User-Agent","value":"insomnia/10.2.0"}],"authentication":{},"metaSortKey":-1734549120583,"isPrivate":false,"pathParameters":[],"settingStoreCookies":true,"settingSendCookies":true,"settingDisableRenderRequestBody":false,"settingEncodeUrl":true,"settingRebuildPath":true,"settingFollowRedirects":"global","_type":"request"},{"_id":"req_a1fd9121c465492db4b345e695bd80ed","parentId":"fld_6491cb41d5074b1d8655948f00f3081f","modified":1734548984273,"created":1734548918228,"url":"http://127.0.0.1:8000/api/professores/","name":"Professor","description":"","method":"GET","body":{"mimeType":"application/json","text":""},"parameters":[],"headers":[{"name":"Content-Type","value":"application/json"},{"name":"User-Agent","value":"insomnia/10.2.0"}],"authentication":{},"metaSortKey":-1734548928964,"isPrivate":false,"pathParameters":[],"settingStoreCookies":true,"settingSendCookies":true,"settingDisableRenderRequestBody":false,"settingEncodeUrl":true,"settingRebuildPath":true,"settingFollowRedirects":"global","_type":"request"},{"_id":"fld_6491cb41d5074b1d8655948f00f3081f","parentId":"wrk_991f9da46bd14e3da11302c4cc68657f","modified":1734548913718,"created":1734548913718,"name":"Professor","description":"","environment":{},"environmentPropertyOrder":null,"metaSortKey":-1734548913718,"environmentType":"kv","_type":"request_group"},{"_id":"req_03f93d31fbf243d88abc42b9ca8f3b18","parentId":"fld_6491cb41d5074b1d8655948f00f3081f","modified":1734548998201,"created":1734548936431,"url":"http://127.0.0.1:8000/api/professores/","name":"Professor","description":"","method":"POST","body":{"mimeType":"application/json","text":"{\n    \"nome\": \"Prof. Herbert\",\n    \"materias\": [3, 4] \n}\n"},"parameters":[],"headers":[{"name":"Content-Type","value":"application/json"},{"name":"User-Agent","value":"insomnia/10.2.0"}],"authentication":{},"metaSortKey":-1734548928864,"isPrivate":false,"pathParameters":[],"settingStoreCookies":true,"settingSendCookies":true,"settingDisableRenderRequestBody":false,"settingEncodeUrl":true,"settingRebuildPath":true,"settingFollowRedirects":"global","_type":"request"},{"_id":"req_56e049987c1243ea924bbb45ab0490c6","parentId":"fld_6491cb41d5074b1d8655948f00f3081f","modified":1734549068476,"created":1734549001658,"url":"http://127.0.0.1:8000/api/professores/1/","name":"Professor","description":"","method":"PUT","body":{"mimeType":"application/json","text":"{\n    \"nome\": \"Prof. Herbert Rausch\",\n    \"materias\": [3, 4]\n}\n"},"parameters":[],"headers":[{"name":"Content-Type","value":"application/json"},{"name":"User-Agent","value":"insomnia/10.2.0"}],"authentication":{},"metaSortKey":-1734548928764,"isPrivate":false,"pathParameters":[],"settingStoreCookies":true,"settingSendCookies":true,"settingDisableRenderRequestBody":false,"settingEncodeUrl":true,"settingRebuildPath":true,"settingFollowRedirects":"global","_type":"request"},{"_id":"req_0a5970d3de7b4fce928d00b2277b385d","parentId":"fld_6491cb41d5074b1d8655948f00f3081f","modified":1734549087157,"created":1734549073959,"url":"http://127.0.0.1:8000/api/professores/1/","name":"Professor","description":"","method":"DELETE","body":{},"parameters":[],"headers":[{"name":"User-Agent","value":"insomnia/10.2.0"}],"authentication":{},"metaSortKey":-1734548928664,"isPrivate":false,"pathParameters":[],"settingStoreCookies":true,"settingSendCookies":true,"settingDisableRenderRequestBody":false,"settingEncodeUrl":true,"settingRebuildPath":true,"settingFollowRedirects":"global","_type":"request"},{"_id":"req_b1ff1cf392c246e5a5d62e218341c802","parentId":"fld_3d3aa5a82de84e90abcfe9a029da2d2a","modified":1734548903521,"created":1734547143231,"url":"http://127.0.0.1:8000/api/alunos/","name":"Aluno","description":"","method":"GET","body":{},"parameters":[],"headers":[{"name":"User-Agent","value":"insomnia/10.2.0"}],"authentication":{},"metaSortKey":-1734547191349,"isPrivate":false,"pathParameters":[],"settingStoreCookies":true,"settingSendCookies":true,"settingDisableRenderRequestBody":false,"settingEncodeUrl":true,"settingRebuildPath":true,"settingFollowRedirects":"global","_type":"request"},{"_id":"fld_3d3aa5a82de84e90abcfe9a029da2d2a","parentId":"wrk_991f9da46bd14e3da11302c4cc68657f","modified":1734547136937,"created":1734547136937,"name":"Aluno","description":"","environment":{},"environmentPropertyOrder":null,"metaSortKey":-1734547136937,"environmentType":"kv","_type":"request_group"},{"_id":"req_43e89a8fef504b30a940124ab81cb89b","parentId":"fld_3d3aa5a82de84e90abcfe9a029da2d2a","modified":1734554403335,"created":1734547195384,"url":"http://127.0.0.1:8000/api/alunos/","name":"Aluno","description":"","method":"POST","body":{"mimeType":"application/json","text":"{\n\t\"id\": 8,\n\t\"matricula\": \"20240\",\n\t\"ano_ingresso\": 2023,\n\t\"nome\": \"Gabriel\",\n\t\"foto\": null,\n\t\"materias\": [3,4]\n}"},"parameters":[],"headers":[{"name":"Content-Type","value":"application/json"},{"name":"User-Agent","value":"insomnia/10.2.0","id":"pair_532df5e5b2bd49b685f908ba17c18d4e"},{"id":"pair_2fc657e5f51a4a5db6f929a4d34f9534","name":"","value":"","description":"","disabled":false}],"authentication":{},"metaSortKey":-1734547191299,"isPrivate":false,"pathParameters":[],"settingStoreCookies":true,"settingSendCookies":true,"settingDisableRenderRequestBody":false,"settingEncodeUrl":true,"settingRebuildPath":true,"settingFollowRedirects":"global","_type":"request"},{"_id":"req_facd833ae14d4476867e7f1e9a5d88f4","parentId":"fld_3d3aa5a82de84e90abcfe9a029da2d2a","modified":1734548882385,"created":1734548829309,"url":"http://127.0.0.1:8000/api/alunos/1/","name":"Aluno","description":"","method":"PUT","body":{"mimeType":"application/json","text":"{\n    \"matricula\": \"20240002\",\n    \"nome\": \"Leticia Mussolin\",\n    \"ano_ingresso\": 2023,\n    \"foto\": null,\n    \"materias\": [3]\n}\n"},"parameters":[],"headers":[{"name":"Content-Type","value":"application/json"},{"name":"User-Agent","value":"insomnia/10.2.0"}],"authentication":{},"metaSortKey":-1734547191249,"isPrivate":false,"pathParameters":[],"settingStoreCookies":true,"settingSendCookies":true,"settingDisableRenderRequestBody":false,"settingEncodeUrl":true,"settingRebuildPath":true,"settingFollowRedirects":"global","_type":"request"},{"_id":"req_4144347eda544d4d970df281007ea28f","parentId":"fld_3d3aa5a82de84e90abcfe9a029da2d2a","modified":1734548901806,"created":1734548887832,"url":"http://127.0.0.1:8000/api/alunos/1/","name":"Aluno","description":"","method":"DELETE","body":{},"parameters":[],"headers":[{"name":"User-Agent","value":"insomnia/10.2.0"}],"authentication":{},"metaSortKey":-1734547190949,"isPrivate":false,"pathParameters":[],"settingStoreCookies":true,"settingSendCookies":true,"settingDisableRenderRequestBody":false,"settingEncodeUrl":true,"settingRebuildPath":true,"settingFollowRedirects":"global","_type":"request"},{"_id":"req_bc7488b2638b4ee78ae2171e70551911","parentId":"fld_8950e293b3c14253a3e908810ab912d1","modified":1734547126642,"created":1734546937659,"url":"http://127.0.0.1:8000/api/materias/","name":"Materia","description":"","method":"GET","body":{},"parameters":[],"headers":[{"name":"User-Agent","value":"insomnia/10.2.0"}],"authentication":{},"metaSortKey":-1734547115965,"isPrivate":false,"pathParameters":[],"settingStoreCookies":true,"settingSendCookies":true,"settingDisableRenderRequestBody":false,"settingEncodeUrl":true,"settingRebuildPath":true,"settingFollowRedirects":"global","_type":"request"},{"_id":"fld_8950e293b3c14253a3e908810ab912d1","parentId":"wrk_991f9da46bd14e3da11302c4cc68657f","modified":1734547109674,"created":1734547109674,"name":"Materia","description":"","environment":{},"environmentPropertyOrder":null,"metaSortKey":-1734547109674,"environmentType":"kv","_type":"request_group"},{"_id":"req_7bea35138f834a31ba1a41b2ef5bc788","parentId":"fld_8950e293b3c14253a3e908810ab912d1","modified":1734548979168,"created":1734546959505,"url":"http://127.0.0.1:8000/api/materias/","name":"Materia","description":"","method":"POST","body":{"mimeType":"application/json","text":"{\n    \"nome\": \"Banco de Dados II\",\n    \"dia_semana\": \"Sexta-feira\",\n    \"professor\": \"Herbert\"\n}\n"},"parameters":[],"headers":[{"name":"Content-Type","value":"application/json"},{"name":"User-Agent","value":"insomnia/10.2.0"}],"authentication":{},"metaSortKey":-1734547115915,"isPrivate":false,"pathParameters":[],"settingStoreCookies":true,"settingSendCookies":true,"settingDisableRenderRequestBody":false,"settingEncodeUrl":true,"settingRebuildPath":true,"settingFollowRedirects":"global","_type":"request"},{"_id":"req_e44c87a349d04c82a61d9e511840bb0c","parentId":"fld_8950e293b3c14253a3e908810ab912d1","modified":1734547377624,"created":1734547012819,"url":"http://127.0.0.1:8000/api/materias/3/","name":"Materia","description":"","method":"PUT","body":{"mimeType":"application/json","text":"{\n    \"nome\": \"Programação Web II\",\n    \"dia_semana\": \"Quinta-feira\",\n    \"professor\": \"Prof. Herbert\"\n}\n"},"parameters":[],"headers":[{"name":"Content-Type","value":"application/json"},{"name":"User-Agent","value":"insomnia/10.2.0"}],"authentication":{},"metaSortKey":-1734547115865,"isPrivate":false,"pathParameters":[],"settingStoreCookies":true,"settingSendCookies":true,"settingDisableRenderRequestBody":false,"settingEncodeUrl":true,"settingRebuildPath":true,"settingFollowRedirects":"global","_type":"request"},{"_id":"req_9583ed3509ea4af39724b39f3b725fe3","parentId":"fld_8950e293b3c14253a3e908810ab912d1","modified":1734547115827,"created":1734547059588,"url":"http://127.0.0.1:8000/api/materias/2/","name":"Materia","description":"","method":"DELETE","body":{},"parameters":[],"headers":[{"name":"User-Agent","value":"insomnia/10.2.0"}],"authentication":{},"metaSortKey":-1734547115765,"isPrivate":false,"pathParameters":[],"settingStoreCookies":true,"settingSendCookies":true,"settingDisableRenderRequestBody":false,"settingEncodeUrl":true,"settingRebuildPath":true,"settingFollowRedirects":"global","_type":"request"},{"_id":"env_01d5d335b97450e3dd33aaddec030ae827383ca3","parentId":"wrk_991f9da46bd14e3da11302c4cc68657f","modified":1734546930849,"created":1734546930849,"name":"Base Environment","data":{},"dataPropertyOrder":null,"color":null,"isPrivate":false,"metaSortKey":1734546930849,"environmentType":"kv","_type":"environment"},{"_id":"jar_01d5d335b97450e3dd33aaddec030ae827383ca3","parentId":"wrk_991f9da46bd14e3da11302c4cc68657f","modified":1734546930851,"created":1734546930851,"name":"Default Jar","cookies":[],"_type":"cookie_jar"}]}